{
    "AX": {
        "error": 0.005690574780539553,
        "error_type": "SEM",
        "filter_outliers_dict": {
            "filter_outliers": true,
            "iterations": 1,
            "std_devs": 2
        },
        "fit": "Average",
        "fn": 58,
        "include_baseline_error": false,
        "n": 60,
        "reviewed": true,
        "value": -0.010018147823349612
    },
    "CDD": {
        "error": 5.466230051053059e-06,
        "error_type": "SEM",
        "filter_outliers_dict": {
            "filter_outliers": true,
            "iterations": 1,
            "std_devs": 10
        },
        "fit": "Average",
        "fn": 60,
        "include_baseline_error": false,
        "n": 60,
        "reviewed": true,
        "value": 1.265952960238792e-05
    },
    "H1": {
        "error": 0.004745005911466769,
        "error_type": "SEM",
        "filter_outliers_dict": {
            "filter_outliers": true,
            "iterations": 1,
            "std_devs": 2
        },
        "fit": "Average",
        "fn": 59,
        "include_baseline_error": false,
        "n": 60,
        "reviewed": true,
        "value": 0.0081226302284187
    },
    "H2": {
        "error": 0.01732543917086337,
        "error_type": "SEM",
        "filter_outliers_dict": {
            "filter_outliers": true,
            "iterations": 1,
            "std_devs": 2
        },
        "fit": "average",
        "value": 0.02349064347030237
    },
    "L1": {
        "error": 0.0027136679934883015,
        "error_type": "SEM",
        "filter_outliers_dict": {
            "filter_outliers": true,
            "iterations": 1,
            "std_devs": 2
        },
        "fit": "Average",
        "fn": 58,
        "include_baseline_error": false,
        "n": 60,
        "reviewed": true,
        "value": -0.05476788988593837
    },
    "L2": {
        "error": 0.0062633435359364595,
        "error_type": "SEM",
        "filter_outliers_dict": {
            "filter_outliers": true,
            "iterations": 1,
            "std_devs": 2
        },
        "fit": "Average",
        "fn": 58,
        "include_baseline_error": false,
        "n": 60,
        "reviewed": true,
        "value": -0.04718884020433601
    }
}